NIDS/__init__.py
NIDS/infer.py
NIDS/train.py
NIDS/utils.py
AutoZeekWatch-0.1.3.dist-info/LICENSE
AutoZeekWatch-0.1.3.dist-info/METADATA
AutoZeekWatch-0.1.3.dist-info/WHEEL
AutoZeekWatch-0.1.3.dist-info/top_level.txt
AutoZeekWatch-0.1.3.dist-info/RECORD
