Metadata-Version: 2.1
Name: AutoZeekWatch
Version: 0.1.3
Summary: Network Intrusion Detection using Zeek logs
Home-page: https://github.com/NYU-HSRN-Network-Data-Science-Group/NIDS/
License: MIT
Project-URL: Documentation, https://github.com/NYU-HSRN-Network-Data-Science-Group/NIDS
Project-URL: Bug Reports, https://github.com/NYU-HSRN-Network-Data-Science-Group/NIDS/issues
Project-URL: Source Code, https://github.com/NYU-HSRN-Network-Data-Science-Group/NIDS
Requires-Python: >=3.6
License-File: LICENSE
Requires-Dist: joblib ==1.3.2
Requires-Dist: matplotlib ==3.7.0
Requires-Dist: mlflow ==2.2.1
Requires-Dist: numpy ==1.23.5
Requires-Dist: pandas ==1.4.2
Requires-Dist: pyod ==1.1.0
Requires-Dist: pysad ==0.2.0
Requires-Dist: scikit-learn ==1.3.2
Requires-Dist: seaborn ==0.11.2
Requires-Dist: tailer ==0.4.1
Requires-Dist: combo ==0.1.3
